gersemi/__init__.py
gersemi/__main__.py
gersemi/__version__.py
gersemi/ast_helpers.py
gersemi/base_command_invocation_dumper.py
gersemi/base_dumper.py
gersemi/builtin_commands.py
gersemi/cache.py
gersemi/cmake.lark
gersemi/command_invocation_dumper.py
gersemi/command_line_formatter.py
gersemi/configuration.py
gersemi/configuration_reports.py
gersemi/custom_command_definition_finder.py
gersemi/dumper.py
gersemi/enum_with_metadata.py
gersemi/exceptions.py
gersemi/extension_type.py
gersemi/extensions.py
gersemi/formatted_file.py
gersemi/formatter.py
gersemi/immutable.py
gersemi/keyword_kind.py
gersemi/keyword_preprocessor.py
gersemi/keyword_with_pairs_formatter.py
gersemi/keywords.py
gersemi/mode.py
gersemi/noop.py
gersemi/parser.py
gersemi/parsing_transformer.py
gersemi/postprocessor.py
gersemi/print_config_kind.py
gersemi/result.py
gersemi/return_codes.py
gersemi/runner.py
gersemi/sanity_checker.py
gersemi/task_result.py
gersemi/transformer.py
gersemi/types.py
gersemi/utils.py
gersemi/warnings.py
gersemi/specializations/__init__.py
gersemi/specializations/add_custom_target.py
gersemi/specializations/argument_aware_command_invocation_dumper.py
gersemi/specializations/condition_syntax_command_invocation_dumper.py
gersemi/specializations/multiple_signature_command_invocation_dumper.py
gersemi/specializations/preserving_command_invocation_dumper.py
gersemi/specializations/section_aware_command_invocation_dumper.py
gersemi/specializations/set_property.py
gersemi/specializations/standard_command_dumper.py
gersemi/specializations/two_word_keyword_isolator.py
gersemi/tasks/__init__.py
gersemi/tasks/check_and_show_diff.py
gersemi/tasks/check_formatting.py
gersemi/tasks/do_nothing.py
gersemi/tasks/format_file.py
gersemi/tasks/forward_to_stdout.py
gersemi/tasks/rewrite_in_place.py
gersemi/tasks/show_diff.py
gersemi-0.25.4.dist-info/licenses/LICENSE
gersemi-0.25.4.dist-info/METADATA
gersemi-0.25.4.dist-info/WHEEL
gersemi-0.25.4.dist-info/entry_points.txt
gersemi-0.25.4.dist-info/top_level.txt
gersemi-0.25.4.dist-info/RECORD
