Metadata-Version: 2.4
Name: gersemi
Version: 0.25.4
Summary: A formatter to make your CMake code the real treasure
Author-email: Blank Spruce <blankspruce@protonmail.com>
License: MPL-2.0
Project-URL: Homepage, https://github.com/BlankSpruce/gersemi
Classifier: Development Status :: 5 - Production/Stable
Classifier: Environment :: Console
Classifier: Intended Audience :: Developers
Classifier: Operating System :: OS Independent
Classifier: Programming Language :: Python :: 3
Classifier: Programming Language :: Python :: 3.8
Classifier: Programming Language :: Python :: 3.9
Classifier: Programming Language :: Python :: 3.10
Classifier: Programming Language :: Python :: 3.11
Classifier: Programming Language :: Python :: 3.12
Classifier: Programming Language :: Python :: 3.13
Classifier: Programming Language :: Python :: 3.14
Classifier: Topic :: Software Development :: Libraries :: Python Modules
Classifier: Topic :: Software Development :: Quality Assurance
Requires-Python: >=3.8
License-File: LICENSE
Requires-Dist: ignore-python<0.4,>=0.3
Requires-Dist: lark>=1.0
Requires-Dist: platformdirs
Requires-Dist: pyyaml<7,>=5
Provides-Extra: color
Requires-Dist: colorama>=0.4; extra == "color"
Dynamic: license-file
